README.md
setup.py
Eventory.egg-info/PKG-INFO
Eventory.egg-info/SOURCES.txt
Eventory.egg-info/dependency_links.txt
Eventory.egg-info/requires.txt
Eventory.egg-info/top_level.txt
eventory/__init__.py
eventory/__version__.py
eventory/eventorial.py
eventory/eventory.py
eventory/exceptions.py
eventory/instructor.py
eventory/narrator.py
eventory/parser.py
eventory/ext/__init__.py
eventory/ext/discord.py
eventory/ext/inktory.py