Metadata-Version: 1.0
Name: Eventory
Version: 0.0.6
Summary: Story time!
Home-page: https://github.com/siku2/Eventory
Author: siku2
Author-email: siku2@outlook.com
License: MIT
Platform: UNKNOWN
